mercury.cpython-311-darwin.so
mercury_python.dylibs/libcrypto.3.dylib
mercury_python-2.13.1.dist-info/RECORD
mercury_python-2.13.1.dist-info/WHEEL
mercury_python-2.13.1.dist-info/top_level.txt
mercury_python-2.13.1.dist-info/METADATA
mercury_python-2.13.1.dist-info/licenses/LICENSE
mercury_python-2.13.1.dist-info/licenses/COPYING
