Metadata-Version: 2.4
Name: mercury-python
Version: 2.13.1
Summary: Python interface into mercury's network protocol fingerprinting and analysis functionality
Home-page: https://github.com/cisco/mercury-python/
Author: Blake Anderson
Author-email: blake.anderson@cisco.com
Keywords: tls fingerprinting network traffic analysis
Classifier: Development Status :: 3 - Alpha
Classifier: Programming Language :: Python :: 3 :: Only
Classifier: Topic :: System :: Networking :: Monitoring
Classifier: Topic :: Security
Requires-Python: >=3.6.0
License-File: LICENSE
License-File: COPYING
Dynamic: author
Dynamic: author-email
Dynamic: classifier
Dynamic: description
Dynamic: description-content-type
Dynamic: home-page
Dynamic: keywords
Dynamic: license-file
Dynamic: requires-python
Dynamic: summary
